aurora_tr/__init__.py
aurora_tr/aurora_tr.py
aurora_tr-0.1.1.dist-info/METADATA
aurora_tr-0.1.1.dist-info/WHEEL
aurora_tr-0.1.1.dist-info/entry_points.txt
aurora_tr-0.1.1.dist-info/RECORD
