Metadata-Version: 2.3
Name: aurora-tr
Version: 0.1.1
Summary: Translate via aurora and variants, openai, azure openai, etc.
Author: ffreemt
Requires-Python: >=3.8
Requires-Dist: joblib>=1.3.2
Requires-Dist: loguru>=0.7.2
Requires-Dist: openai>=1.16.2
Requires-Dist: python-dotenv>=1.0.1
Requires-Dist: rich>=13.7.1
Requires-Dist: stamina>=24.2.0
Requires-Dist: validators>=0.28.0
